pyvalues/__init__.py
pyvalues/classifiers.py
pyvalues/radarplot.py
pyvalues/values.py
pyvalues-0.1.0.dist-info/METADATA
pyvalues-0.1.0.dist-info/WHEEL
pyvalues-0.1.0.dist-info/licenses/LICENSE
pyvalues-0.1.0.dist-info/RECORD
