Metadata-Version: 2.4
Name: pyvalues
Version: 0.1.0
Summary: Python library for processing, evaluating, and visualizing (Schwartz) human value scores
License: MIT License
License-File: LICENSE
Keywords: ai,artificial intelligence,classification,human values,schwartz values,vallueeval
Author: Johannes Kiesel
Maintainer: Johannes Kiesel
Maintainer-email: Johannes.Kiesel@gesis.org
Requires-Python: >=3.11,<3.15
Classifier: License :: Other/Proprietary License
Classifier: Programming Language :: Python :: 3
Classifier: Programming Language :: Python :: 3.11
Classifier: Programming Language :: Python :: 3.12
Classifier: Programming Language :: Python :: 3.13
Classifier: Programming Language :: Python :: 3.14
Requires-Dist: matplotlib (>=3.10.8,<4.0.0)
Requires-Dist: numpy (>=2.4.1,<3.0.0)
Requires-Dist: pandas (>=2.3.3,<3.0.0)
Requires-Dist: pydantic (>=2.12.3,<3.0.0)
Project-URL: Issues, https://github.com/ValueEval/pyvalues/issues
Project-URL: Source, https://github.com/ValueEval/pyvalues
